CHANGES.txt
LICENSE
MANIFEST.in
README.rst
setup.cfg
setup.py
tox.ini
django_reportmail.egg-info/PKG-INFO
django_reportmail.egg-info/SOURCES.txt
django_reportmail.egg-info/dependency_links.txt
django_reportmail.egg-info/not-zip-safe
django_reportmail.egg-info/requires.txt
django_reportmail.egg-info/top_level.txt
reportmail/__init__.py
reportmail/command.py
reportmail/reporter.py
reportmail/templates/reportmail/command_report.txt
reportmail/templates/reportmail/test/report.txt